ihsm_analytics/__init__.py
ihsm_analytics/ar.cp37-win_amd64.pyd
ihsm_analytics/eor.cp37-win_amd64.pyd
ihsm_analytics/screening_table.csv
ihsm_analytics/screening_table_2019.csv
ihsm_analytics/DataFiles/Marcellus Shale/CostModel/cost_model.xgb
ihsm_analytics/DataFiles/Marcellus Shale/GeoModel/isip (psia) median blended.pickle
ihsm_analytics/DataFiles/Marcellus Shale/GeoModel/tvd (ft) blended.pickle
ihsm_analytics/DataFiles/Marcellus Shale/GeoModel/youngs modulus.pickle
ihsm_analytics/DataFiles/Marcellus Shale/Model/10/model.pickle
ihsm_analytics/DataFiles/Marcellus Shale/Model/10/modelPredictTest.csv
ihsm_analytics/DataFiles/Marcellus Shale/Model/12/model.pickle
ihsm_analytics/DataFiles/Marcellus Shale/Model/12/modelPredictTest.csv
ihsm_analytics/DataFiles/Marcellus Shale/Model/14/model.pickle
ihsm_analytics/DataFiles/Marcellus Shale/Model/14/modelPredictTest.csv
ihsm_analytics/DataFiles/Marcellus Shale/Model/16/model.pickle
ihsm_analytics/DataFiles/Marcellus Shale/Model/16/modelPredictTest.csv
ihsm_analytics/DataFiles/Marcellus Shale/Model/18/model.pickle
ihsm_analytics/DataFiles/Marcellus Shale/Model/18/modelPredictTest.csv
ihsm_analytics/DataFiles/Marcellus Shale/Model/20/model.pickle
ihsm_analytics/DataFiles/Marcellus Shale/Model/20/modelPredictTest.csv
ihsm_analytics/DataFiles/Marcellus Shale/Model/22/model.pickle
ihsm_analytics/DataFiles/Marcellus Shale/Model/22/modelPredictTest.csv
ihsm_analytics/DataFiles/Marcellus Shale/Model/24/model.pickle
ihsm_analytics/DataFiles/Marcellus Shale/Model/24/modelPredictTest.csv
ihsm_analytics/DataFiles/Marcellus Shale/Model/26/model.pickle
ihsm_analytics/DataFiles/Marcellus Shale/Model/26/modelPredictTest.csv
ihsm_analytics/DataFiles/Marcellus Shale/Model/28/model.pickle
ihsm_analytics/DataFiles/Marcellus Shale/Model/28/modelPredictTest.csv
ihsm_analytics/DataFiles/Marcellus Shale/Model/30/model.pickle
ihsm_analytics/DataFiles/Marcellus Shale/Model/30/modelPredictTest.csv
ihsm_analytics-0.0.33.dist-info/METADATA
ihsm_analytics-0.0.33.dist-info/WHEEL
ihsm_analytics-0.0.33.dist-info/top_level.txt
ihsm_analytics-0.0.33.dist-info/RECORD
