Metadata-Version: 2.1
Name: ihsm-analytics
Version: 0.0.33
Summary: The package provides advanced geo-analytics functionalities.
Home-page: https://ihsmarkit.com/
Author: Huy Nguyen
Author-email: huy.nguyen@ihsmarkit.com
License: MIT
Platform: UNKNOWN
Classifier: Operating System :: Microsoft :: Windows
Classifier: Topic :: Software Development :: Libraries
Requires-Python: >=3.7
Requires-Dist: numpy
Requires-Dist: pandas
Requires-Dist: scipy
Requires-Dist: sklearn
Requires-Dist: xgboost
